{"canCommit":{"success":{"hash":-3524738586110013018}},"doCommit":{"success":{"hash":-3524738586110013018}},"canPush":{"success":{"hash":-7681562839543473215}},"doPush":{"success":{"hash":-7681562839543473215}},"doMerge":{"success":{"hash":-1358039575920212264}},"canCheckout":{"success":{"hash":-8108511941703536868}},"canPublish":{"success":{"hash":-1358039575920212264}},"doPrepareVersion":{"success":{"hash":-1358039575920212264}},"doPublishPubDev":{"success":{"hash":-1358039575920212264}},"doPublishGit":{"success":{"hash":2744995075888065108}},"doPublish":{"success":{"hash":-1358039575920212264}},"canMerge":{"success":{"hash":-1358039575920212264}}}